{"type":"SoundProcess","_associatedColor":"0x0000ffff","duration":208.7962,"height":0.052,"instrumentRef":"lpf","controls":[{"value":{"type":"Bus","bus":"output"},"name":"bus"},{"value":{"type":"Envelope","points":[{"time":0.0000,"value":20000.000},{"time":107.3472,"value":20000.000},{"time":143.0313,"value":5000.000},{"time":208.7962,"value":5000.000}],"displayColor":"0x00ffffff","display":true},"name":"freq"},{"value":{"type":"Value","value":1,"allocateBus":false},"name":"fade"}],"name":"hpf_2"}