{"type":"ponticello.model.obj.CustomizableSynthDefObject","parameters":{"out":{"type":"bus","rate":"Control","channels":1},"value":{"type":"numerical","defaultValue":"0","min":"0","max":"1","warp":"lin","step":"0.01"}},"color":"0x0000ffff","ugenGraph":{"editor":{"variables":[],"statements":[{"_contentType":"ponticello.sc.editor.MessageSendEditor","receiver":"Out","method":"kr","arguments":["out","value"],"disabled":false}],"_type":"ponticello.sc.editor.CodeBlockEditor"},"controlArguments":{}},"name":"write_kr"}